lidar_aug/__init__.py
lidar_aug/evaluation.cpython-311-x86_64-linux-gnu.so
lidar_aug/evaluation.pyi
lidar_aug/point_cloud.cpython-311-x86_64-linux-gnu.so
lidar_aug/point_cloud.pyi
lidar_aug/transformations.cpython-311-x86_64-linux-gnu.so
lidar_aug/transformations.pyi
lidar_aug/weather_simulations.cpython-311-x86_64-linux-gnu.so
lidar_aug/weather_simulations.pyi
lidar_aug/python/augmentations.py
lidar_aug/python/utils.py
lidar_aug/python/visualization.py
lidar_aug-1.0.1.dist-info/LICENSE
lidar_aug-1.0.1.dist-info/METADATA
lidar_aug-1.0.1.dist-info/NOTICE
lidar_aug-1.0.1.dist-info/WHEEL
lidar_aug-1.0.1.dist-info/top_level.txt
lidar_aug-1.0.1.dist-info/RECORD
