Metadata-Version: 2.1
Name: lidar_aug
Version: 1.0.1
Summary: A toolbox for LiDAR point cloud data, providing point cloud transformations, point cloud augmentation, realistic weather simulation and 2D & 3D AP evaluation, with an easy-to-use Python API. This module supports several essential tasks for the development of LiDAR-based perception methods in automated driving.
Author-email: Tom Schammo <tom.schammo@uni-tuebingen.de>, Sven Teufel <sven.teufel@uni-tuebingen.de>
License: Apache License
Project-URL: Homepage, https://lidaraug.readthedocs.io
Project-URL: Documentation, https://lidaraug.readthedocs.io/en/release-v1.0.1/
Project-URL: Repository, https://github.com/ekut-es/LidarAug/
Project-URL: Issues, https://github.com/ekut-es/LidarAug/issues
Keywords: augmentation,machine learning,LiDAR,self driving,weather simulation
Classifier: Development Status :: 5 - Production/Stable
Classifier: Intended Audience :: Developers
Classifier: Intended Audience :: Science/Research
Classifier: Topic :: Software Development :: Libraries :: Python Modules
Classifier: Topic :: Scientific/Engineering :: Artificial Intelligence
Classifier: Topic :: Scientific/Engineering :: Visualization
Classifier: Topic :: Scientific/Engineering :: Image Processing
Classifier: License :: OSI Approved :: Apache Software License
Classifier: Operating System :: POSIX :: Linux
Classifier: Programming Language :: Python :: 3.11
Requires-Python: <3.12
License-File: LICENSE
License-File: NOTICE
Requires-Dist: torch==2.2.0
Requires-Dist: matplotlib
Requires-Dist: numpy==1.24.0
Requires-Dist: open3d
